rtl/hdl/math_block/math_block.vhd

library IEEE;
use IEEE.std_logic_1164.all;
use IEEE.numeric_std.all;




entity math_block is port ( A1, B1, A2, B2 : in signed(8 downto 0); 
                            C, D: in signed(43 downto 0);
                            clk : in std_logic;
                            P: out signed(43 downto 0)); 
end math_block; 

architecture math_block_arch of math_block is 
begin
    process(clk)
    begin
        if(rising_edge(clk)) then
            P <= (A1*B1) + (A2*B2) + C + D;
        end if;
    end process;
end math_block_arch;

rtl/sim/GHDL/tb_math_block/tb_math_block.vhd
-----------------------------------------
--2to1 multiplexer structural TestBench--
-----------------------------------------

library IEEE;
use IEEE.std_logic_1164.all;
use IEEE.numeric_std.all;

entity testbench_math_block is
-- empty
end testbench_math_block;

architecture tb of testbench_math_block is

--Device Under Test component
component math_block is port ( A1, B1, A2, B2 : in signed(8 downto 0); 
                                C, D: in signed(43 downto 0);
                                clk : in std_logic;
                                P: out signed(43 downto 0)); 
end component; 

signal A1, B1, A2, B2 : signed(8 downto 0); 
signal C, D : signed(43 downto 0);
signal clk : std_logic;
signal P : signed(43 downto 0);

begin

	--Connect DUT
    DUT: math_block port map ( A1 => A1, B1 => B1, A2 => A2, B2 => B2, 
                               C => C, D => D, clk => clk, P => P);

    clk_process: process
		begin
        clk <= '0';
    	wait for 2 ns;
    	clk <= '1';
    	wait for 2 ns;
	end process;

    process
    begin
    	A1 <= (others => '0');
        B1 <= (others => '0');
        A2 <= (others => '0');
        B2 <= (others => '0');
        C <= (others => '0');
        D <= (others => '0');
        wait for 8 ns;

        A1 <= to_signed(127, 9);-- 0.9921875 in signed Q0.7
        B1 <= to_signed(90, 9);
        wait for 8 ns;
        --89.296875 -> 0b10110010100110 (2CA6)
        

        A1 <= (others => '0');
        B1 <= (others => '0');
        A2 <= to_signed(127, 9);-- 0.9921875 in signed Q0.7
        B2 <= to_signed(90, 9);
        wait for 8 ns;
        --89.296875 -> 0b10110010100110

        A2 <= (others => '0');
        B2 <= (others => '0');
        C <= to_signed(127, 44);
        wait for 8 ns;
        
        C <= (others => '0');
        D <= to_signed(-128, 44);
        wait for 8 ns;
        
        ---Clear inputs
        A1 <= (others => '0');
        B1 <= (others => '0');
        A2 <= (others => '0');
        B2 <= (others => '0');
        C <= (others => '0');
        D <= (others => '0');
        
        wait;
	end process;
end tb;

rtl/sim/GHDL/tb_math_block/math_block.vcd
$date
  Tue Jan 30 11:33:52 2024
$end
$version
  GHDL v0
$end
$timescale
  1 fs
$end
$scope module standard $end
$upscope $end
$scope module std_logic_1164 $end
$upscope $end
$scope module numeric_std $end
$upscope $end
$scope module testbench_math_block $end
$var reg 9 ! a1[8:0] $end
$var reg 9 " b1[8:0] $end
$var reg 9 # a2[8:0] $end
$var reg 9 $ b2[8:0] $end
$var reg 44 % c[43:0] $end
$var reg 44 & d[43:0] $end
$var reg 1 ' clk $end
$var reg 44 ( p[43:0] $end
$scope module dut $end
$var reg 9 ) a1[8:0] $end
$var reg 9 * b1[8:0] $end
$var reg 9 + a2[8:0] $end
$var reg 9 , b2[8:0] $end
$var reg 44 - c[43:0] $end
$var reg 44 . d[43:0] $end
$var reg 1 / clk $end
$var reg 44 0 p[43:0] $end
$upscope $end
$upscope $end
$enddefinitions $end
#0
b000000000 !
b000000000 "
b000000000 #
b000000000 $
b00000000000000000000000000000000000000000000 %
b00000000000000000000000000000000000000000000 &
0'
bUUUUUUUUUUUUUUUUUUUUUUUUUUUUUUUUUUUUUUUUUUUU (
b000000000 )
b000000000 *
b000000000 +
b000000000 ,
b00000000000000000000000000000000000000000000 -
b00000000000000000000000000000000000000000000 .
0/
bUUUUUUUUUUUUUUUUUUUUUUUUUUUUUUUUUUUUUUUUUUUU 0
#2000000
1'
b00000000000000000000000000000000000000000000 (
1/
b00000000000000000000000000000000000000000000 0
#4000000
0'
0/
#6000000
1'
1/
#8000000
b001111111 !
b001011010 "
0'
b001111111 )
b001011010 *
0/
#10000000
1'
b00000000000000000000000000000010110010100110 (
1/
b00000000000000000000000000000010110010100110 0
#12000000
0'
0/
#14000000
1'
1/
#16000000
b000000000 !
b000000000 "
b001111111 #
b001011010 $
0'
b000000000 )
b000000000 *
b001111111 +
b001011010 ,
0/
#18000000
1'
1/
#20000000
0'
0/
#22000000
1'
1/
#24000000
b000000000 #
b000000000 $
b00000000000000000000000000000000000001111111 %
0'
b000000000 +
b000000000 ,
b00000000000000000000000000000000000001111111 -
0/
#26000000
1'
b00000000000000000000000000000000000001111111 (
1/
b00000000000000000000000000000000000001111111 0
#28000000
0'
0/
#30000000
1'
1/
#32000000
b00000000000000000000000000000000000000000000 %
b11111111111111111111111111111111111110000000 &
0'
b00000000000000000000000000000000000000000000 -
b11111111111111111111111111111111111110000000 .
0/
#34000000
1'
b11111111111111111111111111111111111110000000 (
1/
b11111111111111111111111111111111111110000000 0
#36000000
0'
0/
#38000000
1'
1/
#40000000
b00000000000000000000000000000000000000000000 &
0'
b00000000000000000000000000000000000000000000 .
0/
#42000000
1'
b00000000000000000000000000000000000000000000 (
1/
b00000000000000000000000000000000000000000000 0
